covid19dashboard/__init__.py
covid19dashboard/__main__.py
covid19dashboard/config.py
covid19dashboard/covid_data_handler.py
covid19dashboard/covid_news_handler.py
covid19dashboard/covid_news_handling.py
covid19dashboard/logger.py
covid19dashboard/scheduler.py
tests/__init__.py
tests/test_config.py
tests/test_covid_data_handler.py
tests/test_covid_news_handler.py
tests/test_covid_news_handling.py
tests/test_logger.py
tests/test_scheduler.py
covid19_dashboard_pkg_hwhittle-0.0.5.dist-info/LICENSE
covid19_dashboard_pkg_hwhittle-0.0.5.dist-info/METADATA
covid19_dashboard_pkg_hwhittle-0.0.5.dist-info/WHEEL
covid19_dashboard_pkg_hwhittle-0.0.5.dist-info/top_level.txt
covid19_dashboard_pkg_hwhittle-0.0.5.dist-info/RECORD
