Metadata-Version: 2.1
Name: covid19-dashboard-pkg-hwhittle
Version: 0.0.5
Summary: A personalisable UK COVID-19 Dashboard used for demonstration purposes.
Home-page: https://github.com/itselectroz/covid-dashboard-coursework
Author: Harry Whittle
Author-email: harry.whittle@cwgsy.net
License: UNKNOWN
Platform: UNKNOWN
Classifier: Programming Language :: Python :: 3
Classifier: License :: OSI Approved :: GNU General Public License v3 (GPLv3)
Classifier: Operating System :: OS Independent
Requires-Python: >=3.6
License-File: LICENSE
